bass/__init__.py
bass/hubkey.py
opp_bass-1.0.11.dist-info/DESCRIPTION.rst
opp_bass-1.0.11.dist-info/METADATA
opp_bass-1.0.11.dist-info/metadata.json
opp_bass-1.0.11.dist-info/pbr.json
opp_bass-1.0.11.dist-info/RECORD
opp_bass-1.0.11.dist-info/top_level.txt
opp_bass-1.0.11.dist-info/WHEEL
