Metadata-Version: 2.0
Name: opp-bass
Version: 1.0.11
Summary: Open Permissions Platform Identity Library
Home-page: https://github.com/openpermissions/bass
Author: The Open Permissions Platform Coalition
Author-email: support@openpermissions.org
License: Apache 2.0
Platform: UNKNOWN
Classifier: Development Status :: 5 - Production/Stable
Classifier: Intended Audience :: Developers
Classifier: Natural Language :: English
Classifier: License :: OSI Approved :: Apache Software License
Classifier: Programming Language :: Python
Classifier: Programming Language :: Python :: 2.7
Classifier: Programming Language :: Python :: Implementation :: CPython
